SPOJ/__init__.py
SPOJ/cli.py
SPOJ_CMD-0.0.1.data/scripts/cli.py
SPOJ_CMD-0.0.1.dist-info/DESCRIPTION.rst
SPOJ_CMD-0.0.1.dist-info/METADATA
SPOJ_CMD-0.0.1.dist-info/RECORD
SPOJ_CMD-0.0.1.dist-info/WHEEL
SPOJ_CMD-0.0.1.dist-info/entry_points.txt
SPOJ_CMD-0.0.1.dist-info/metadata.json
SPOJ_CMD-0.0.1.dist-info/top_level.txt
