Metadata-Version: 2.0
Name: SPOJ-CMD
Version: 0.0.1
Summary: Python command line client to access SPOJ problems
Home-page: https://github.com/amoghj8/spoj-cmd
Author: Amogh A Joshi
Author-email: amoghj8@gmail.com
License: MIT
Keywords: spoj cli competitiveprogramming developer
Platform: UNKNOWN
